{
  "name": "kx 的软件源",
  "subtitle": "个人收集的 iOS 应用",
  "description": "这是我的个人 AltStore 软件源，会持续更新",
  "iconURL": "https://raw.githubusercontent.com/Leonleoi/kx-/main/d05d7a0d40f3e19891afa045b766e0d7.jpg",
  "website": "https://github.com/Leonleoi/kx-",
  "tintColor": "3B82F6",
  "apps": [
    {
      "name": "Calculator",
      "bundleIdentifier": "com.leonleoi.calculator",
      "developerName": "kx",
      "subtitle": "计算器应用",
      "localizedDescription": "一个简洁好用的计算器应用",
      "iconURL": "https://raw.githubusercontent.com/Leonleoi/kx-/main/d05d7a0d40f3e19891afa045b766e0d7.jpg",
      "tintColor": "10B981",
      "versions": [
        {
          "version": "1.0",
          "date": "2026-05-08",
          "localizedDescription": "首个版本",
          "downloadURL": "https://raw.githubusercontent.com/Leonleoi/kx-/main/Calculator-unsigned.ipa",
          "size": 73611
        }
      ]
    },
    {
      "name": "欢乐斗地主",
      "bundleIdentifier": "com.leonleoi.doudizhu",
      "developerName": "kx",
      "subtitle": "无限金币钻石版",
      "localizedDescription": "欢乐斗地主 7.7 版本，无限金币无限钻石",
      "iconURL": "https://raw.githubusercontent.com/Leonleoi/kx-/main/d05d7a0d40f3e19891afa045b766e0d7.jpg",
      "tintColor": "F59E0B",
      "versions": [
        {
          "version": "7.7",
          "date": "2026-05-08",
          "localizedDescription": "无限金币钻石版",
          "downloadURL": "https://raw.githubusercontent.com/Leonleoi/kx-/main/doudizhu.ipa",
          "size": 86199354
        }
      ]
    }
  ]
}
